slide_gpt/__init__.py
slide_gpt/main.py
slide_gpt-0.3.2.dist-info/LICENSE
slide_gpt-0.3.2.dist-info/METADATA
slide_gpt-0.3.2.dist-info/WHEEL
slide_gpt-0.3.2.dist-info/entry_points.txt
slide_gpt-0.3.2.dist-info/RECORD
