Metadata-Version: 2.1
Name: slide-gpt
Version: 0.3.2
Summary: CLI tool for generating slides from text using ChatGPT and DALL-E
Author: Alex Jercan
Author-email: jercan_alex27@yahoo.com
Requires-Python: >=3.10,<4.0
Classifier: Programming Language :: Python :: 3
Classifier: Programming Language :: Python :: 3.10
Classifier: Programming Language :: Python :: 3.11
Requires-Dist: fakeyou (>=1.2.5,<2.0.0)
Requires-Dist: ffmpeg-python (>=0.2.0,<0.3.0)
Requires-Dist: mypy (>=1.5.1,<2.0.0)
Requires-Dist: openai (>=0.27.8,<0.28.0)
Requires-Dist: tqdm (>=4.66.1,<5.0.0)
Requires-Dist: wave (>=0.0.2,<0.0.3)
